ellar_sql/__init__.py
ellar_sql/constant.py
ellar_sql/module.py
ellar_sql/py.typed
ellar_sql/schemas.py
ellar_sql/session.py
ellar_sql/types.py
ellar_sql/cli/__init__.py
ellar_sql/cli/commands.py
ellar_sql/cli/handlers.py
ellar_sql/factory/__init__.py
ellar_sql/factory/base.py
ellar_sql/migrations/__init__.py
ellar_sql/migrations/base.py
ellar_sql/migrations/multiple.py
ellar_sql/migrations/single.py
ellar_sql/model/__init__.py
ellar_sql/model/base.py
ellar_sql/model/database_binds.py
ellar_sql/model/mixins.py
ellar_sql/model/table.py
ellar_sql/model/utils.py
ellar_sql/model/typeDecorator/__init__.py
ellar_sql/model/typeDecorator/guid.py
ellar_sql/model/typeDecorator/ipaddress.py
ellar_sql/model/typeDecorator/file/__init__.py
ellar_sql/model/typeDecorator/file/exceptions.py
ellar_sql/model/typeDecorator/file/file.py
ellar_sql/model/typeDecorator/file/file_tracker.py
ellar_sql/model/typeDecorator/file/processors.py
ellar_sql/model/typeDecorator/file/types.py
ellar_sql/model/typeDecorator/file/validators.py
ellar_sql/pagination/__init__.py
ellar_sql/pagination/base.py
ellar_sql/pagination/decorator.py
ellar_sql/pagination/utils.py
ellar_sql/pagination/view.py
ellar_sql/query/__init__.py
ellar_sql/query/utils.py
ellar_sql/services/__init__.py
ellar_sql/services/base.py
ellar_sql/services/metadata_engine.py
ellar_sql/templates/multiple/README
ellar_sql/templates/multiple/alembic.ini.mako
ellar_sql/templates/multiple/env.py
ellar_sql/templates/multiple/script.py.mako
ellar_sql/templates/single/README
ellar_sql/templates/single/alembic.ini.mako
ellar_sql/templates/single/env.py
ellar_sql/templates/single/script.py.mako
ellar_sql-0.1.6.dist-info/licenses/LICENSE
ellar_sql-0.1.6.dist-info/WHEEL
ellar_sql-0.1.6.dist-info/METADATA
ellar_sql-0.1.6.dist-info/RECORD
