Metadata-Version: 2.4
Name: ellar-sql
Version: 0.1.6
Summary: EllarSQL Module adds support for SQLAlchemy and Alembic package to your Ellar application
Author-email: Ezeudoh Tochukwu <tochukwu.ezeudoh@gmail.com>
Requires-Python: >=3.8
Classifier: Development Status :: 5 - Production/Stable
Classifier: Environment :: Web Environment
Classifier: Intended Audience :: Developers
Classifier: License :: OSI Approved :: MIT License
Classifier: Operating System :: OS Independent
Classifier: Programming Language :: Python
Classifier: Topic :: Internet :: WWW/HTTP :: Dynamic Content
Classifier: Programming Language :: Python :: 3
Classifier: Programming Language :: Python :: 3.8
Classifier: Programming Language :: Python :: 3.9
Classifier: Programming Language :: Python :: 3.10
Classifier: Programming Language :: Python :: 3.11
Classifier: Programming Language :: Python :: 3 :: Only
License-File: LICENSE
Requires-Dist: ellar-cli >= 0.4.3
Requires-Dist: sqlalchemy >= 2.0.23
Requires-Dist: alembic >= 1.10.0
Requires-Dist: ellar-storage >= 0.1.7
Requires-Dist: sqlalchemy-file >= 0.6.0
Requires-Dist: sqlalchemy[asyncio] >= 2.0.23 ; extra == "async"
Project-URL: Bug Tracker, https://github.com/python-ellar/ellar-sql/issues
Project-URL: Documentation, https://python-ellar.github.io/ellar-sql/
Project-URL: Homepage, https://github.com/python-ellar/ellar-sql
Project-URL: Source, https://github.com/python-ellar/ellar-sql
Provides-Extra: async
